qlikreload/__init__.py
qlikreload/reloader.py
qlikreload-0.1.0.dist-info/METADATA
qlikreload-0.1.0.dist-info/WHEEL
qlikreload-0.1.0.dist-info/top_level.txt
qlikreload-0.1.0.dist-info/RECORD
