Metadata-Version: 2.4
Name: qlikreload
Version: 0.1.0
Summary: Reload Qlik Sense apps via QRS API
Author: Your Name
Classifier: Programming Language :: Python :: 3
Classifier: License :: OSI Approved :: MIT License
Requires-Python: >=3.6
Requires-Dist: requests
Dynamic: author
Dynamic: classifier
Dynamic: requires-dist
Dynamic: requires-python
Dynamic: summary
